listrum/apps/__main__.py
listrum/apps/history.py
listrum/client/__init__.py
listrum/client/crypto.py
listrum/client/error.py
listrum/client/https.py
listrum/client/nodes.py
listrum/node/__init__.py
listrum/node/__main__.py
listrum/node/balance.py
listrum/node/config.py
listrum/node/fee.py
listrum/node/tx/__init__.py
listrum/node/tx/list.py
listrum/node/tx/repay.py
listrum/node/tx/storage.py
Listrum-1.3.0b0.dist-info/LICENCE
Listrum-1.3.0b0.dist-info/METADATA
Listrum-1.3.0b0.dist-info/WHEEL
Listrum-1.3.0b0.dist-info/top_level.txt
Listrum-1.3.0b0.dist-info/RECORD
