Metadata-Version: 2.1
Name: Listrum
Version: 1.3.0b0
Summary: Distributed currency
Author-email: Listrum developers <contact@listrum.com>
Project-URL: Homepage, https://github.com/listrum/node-client
Classifier: Programming Language :: Python :: 3
Classifier: License :: OSI Approved :: MIT License
Classifier: Operating System :: OS Independent
Requires-Python: >=3.9
License-File: LICENCE
